radiosat/__init__.py
radiosat/radiosat.py
radiosat-0.1.0.dist-info/LICENSE
radiosat-0.1.0.dist-info/METADATA
radiosat-0.1.0.dist-info/WHEEL
radiosat-0.1.0.dist-info/top_level.txt
radiosat-0.1.0.dist-info/RECORD
