Metadata-Version: 2.1
Name: radiosat
Version: 0.1.0
Summary: Package to help with the development of tracking algorithms for satellite ground stations
Author-email: Aurélien Genin <aurelien.genin@epfl.ch>
License: GNU GENERAL PUBLIC LICENSE
Classifier: Programming Language :: Python :: 3
Classifier: License :: OSI Approved :: GNU General Public License v3 (GPLv3)
Classifier: Operating System :: OS Independent
Requires-Python: >=3.10
License-File: LICENSE
Requires-Dist: numpy
Requires-Dist: matplotlib
Requires-Dist: pandas
Requires-Dist: tqdm
Requires-Dist: astropy
Requires-Dist: scipy
Requires-Dist: poliastro
Requires-Dist: openturns
Requires-Dist: satastro
